ptcl/__init__.py
ptcl/logger.py
ptcl/protocol.py
ptcl/server/__init__.py
ptcl/server/Server.py
ptcl/socket/__init__.py
ptcl/socket/AbstractSocket.py
ptcl/socket/Socket.py
ptcl/transform/__init__.py
ptcl/transform/Transform.py
ptcl/transform/transforms.py
ptcl-0.1.0.dist-info/LICENCE.txt
ptcl-0.1.0.dist-info/METADATA
ptcl-0.1.0.dist-info/WHEEL
ptcl-0.1.0.dist-info/RECORD
