Metadata-Version: 2.3
Name: ptcl
Version: 0.1.0
Summary: A framework for creating protocols and socket servers
License: MIT
Author: Ahmet Erdem
Author-email: ahmetblk1035@gmail.com
Requires-Python: >=3.9
Classifier: License :: OSI Approved :: MIT License
Classifier: Programming Language :: Python :: 3
Classifier: Programming Language :: Python :: 3.9
Classifier: Programming Language :: Python :: 3.10
Classifier: Programming Language :: Python :: 3.11
Classifier: Programming Language :: Python :: 3.12
Classifier: Programming Language :: Python :: 3.13
